{"_format":"","paths":{"artifacts":"out","build_infos":"out/build-info","sources":"src","tests":"test","scripts":"script","libraries":["lib"]},"files":{"lib/forge-std/lib/ds-test/src/test.sol":{"lastModificationDate":1740402136675,"contentHash":"9febff9d09f18af5306669dc276c4c43","sourceName":"lib/forge-std/lib/ds-test/src/test.sol","imports":[],"versionRequirement":">=0.5.0","artifacts":{"DSTest":{"0.8.26":{"default":{"path":"test.sol/DSTest.json","build_id":"dd64a528eb91b370e71884f52bdf5b7d"}}}},"seenByCompiler":true},"lib/forge-std/src/Base.sol":{"lastModificationDate":1740402135686,"contentHash":"8f04bbbb2c16f79e14fdc321695a8ec2","sourceName":"lib/forge-std/src/Base.sol","imports":["lib/forge-std/src/StdStorage.sol","lib/forge-std/src/Vm.sol"],"versionRequirement":">=0.6.2, <0.9.0","artifacts":{"CommonBase":{"0.8.26":{"default":{"path":"Base.sol/CommonBase.json","build_id":"dd64a528eb91b370e71884f52bdf5b7d"}}},"ScriptBase":{"0.8.26":{"default":{"path":"Base.sol/ScriptBase.json","build_id":"dd64a528eb91b370e71884f52bdf5b7d"}}},"TestBase":{"0.8.26":{"default":{"path":"Base.sol/TestBase.json","build_id":"dd64a528eb91b370e71884f52bdf5b7d"}}}},"seenByCompiler":true},"lib/forge-std/src/Script.sol":{"lastModificationDate":1740402135686,"contentHash":"83c39354c1e43190bce4dc43860dc786","sourceName":"lib/forge-std/src/Script.sol","imports":["lib/forge-std/src/Base.sol","lib/forge-std/src/StdChains.sol","lib/forge-std/src/StdCheats.sol","lib/forge-std/src/StdJson.sol","lib/forge-std/src/StdMath.sol","lib/forge-std/src/StdStorage.sol","lib/forge-std/src/StdUtils.sol","lib/forge-std/src/Vm.sol","lib/forge-std/src/console.sol","lib/forge-std/src/console2.sol","lib/forge-std/src/interfaces/IMulticall3.sol"],"versionRequirement":">=0.6.2, <0.9.0","artifacts":{"Script":{"0.8.26":{"default":{"path":"Script.sol/Script.json","build_id":"dd64a528eb91b370e71884f52bdf5b7d"}}}},"seenByCompiler":true},"lib/forge-std/src/StdAssertions.sol":{"lastModificationDate":1740402135687,"contentHash":"6cc2858240bcd443debbbf075490e325","sourceName":"lib/forge-std/src/StdAssertions.sol","imports":["lib/forge-std/lib/ds-test/src/test.sol","lib/forge-std/src/StdMath.sol"],"versionRequirement":">=0.6.2, <0.9.0","artifacts":{"StdAssertions":{"0.8.26":{"default":{"path":"StdAssertions.sol/StdAssertions.json","build_id":"dd64a528eb91b370e71884f52bdf5b7d"}}}},"seenByCompiler":true},"lib/forge-std/src/StdChains.sol":{"lastModificationDate":1740402135687,"contentHash":"94ba68ea5c34509e1355d69df27597ce","sourceName":"lib/forge-std/src/StdChains.sol","imports":["lib/forge-std/src/Vm.sol"],"versionRequirement":">=0.6.2, <0.9.0","artifacts":{"StdChains":{"0.8.26":{"default":{"path":"StdChains.sol/StdChains.json","build_id":"dd64a528eb91b370e71884f52bdf5b7d"}}}},"seenByCompiler":true},"lib/forge-std/src/StdCheats.sol":{"lastModificationDate":1740402135687,"contentHash":"1f7c1fe2f20a051b847336e1630e4bb5","sourceName":"lib/forge-std/src/StdCheats.sol","imports":["lib/forge-std/src/StdStorage.sol","lib/forge-std/src/Vm.sol"],"versionRequirement":">=0.6.2, <0.9.0","artifacts":{"StdCheats":{"0.8.26":{"default":{"path":"StdCheats.sol/StdCheats.json","build_id":"dd64a528eb91b370e71884f52bdf5b7d"}}},"StdCheatsSafe":{"0.8.26":{"default":{"path":"StdCheats.sol/StdCheatsSafe.json","build_id":"dd64a528eb91b370e71884f52bdf5b7d"}}}},"seenByCompiler":true},"lib/forge-std/src/StdError.sol":{"lastModificationDate":1740402036594,"contentHash":"64c896e1276a291776e5ea5aecb3870a","sourceName":"lib/forge-std/src/StdError.sol","imports":[],"versionRequirement":">=0.6.2, <0.9.0","artifacts":{"stdError":{"0.8.26":{"default":{"path":"StdError.sol/stdError.json","build_id":"dd64a528eb91b370e71884f52bdf5b7d"}}}},"seenByCompiler":true},"lib/forge-std/src/StdInvariant.sol":{"lastModificationDate":1740402135687,"contentHash":"12c06010ec43ce935ed209d5aca30828","sourceName":"lib/forge-std/src/StdInvariant.sol","imports":[],"versionRequirement":">=0.6.2, <0.9.0","artifacts":{"StdInvariant":{"0.8.26":{"default":{"path":"StdInvariant.sol/StdInvariant.json","build_id":"dd64a528eb91b370e71884f52bdf5b7d"}}}},"seenByCompiler":true},"lib/forge-std/src/StdJson.sol":{"lastModificationDate":1740402135687,"contentHash":"2e1d13674e152408867795362d833c24","sourceName":"lib/forge-std/src/StdJson.sol","imports":["lib/forge-std/src/Vm.sol"],"versionRequirement":">=0.6.0, <0.9.0","artifacts":{"stdJson":{"0.8.26":{"default":{"path":"StdJson.sol/stdJson.json","build_id":"dd64a528eb91b370e71884f52bdf5b7d"}}}},"seenByCompiler":true},"lib/forge-std/src/StdMath.sol":{"lastModificationDate":1740402036594,"contentHash":"9da8f453eba6bb98f3d75bc6822bfb29","sourceName":"lib/forge-std/src/StdMath.sol","imports":[],"versionRequirement":">=0.6.2, <0.9.0","artifacts":{"stdMath":{"0.8.26":{"default":{"path":"StdMath.sol/stdMath.json","build_id":"dd64a528eb91b370e71884f52bdf5b7d"}}}},"seenByCompiler":true},"lib/forge-std/src/StdStorage.sol":{"lastModificationDate":1740402135687,"contentHash":"3cb9868082df39a53927db09dbc21f23","sourceName":"lib/forge-std/src/StdStorage.sol","imports":["lib/forge-std/src/Vm.sol"],"versionRequirement":">=0.6.2, <0.9.0","artifacts":{"stdStorage":{"0.8.26":{"default":{"path":"StdStorage.sol/stdStorage.json","build_id":"dd64a528eb91b370e71884f52bdf5b7d"}}},"stdStorageSafe":{"0.8.26":{"default":{"path":"StdStorage.sol/stdStorageSafe.json","build_id":"dd64a528eb91b370e71884f52bdf5b7d"}}}},"seenByCompiler":true},"lib/forge-std/src/StdStyle.sol":{"lastModificationDate":1740402135687,"contentHash":"820e6f6b7704f0c980fae604b1e34b18","sourceName":"lib/forge-std/src/StdStyle.sol","imports":["lib/forge-std/src/Vm.sol"],"versionRequirement":">=0.4.22, <0.9.0","artifacts":{"StdStyle":{"0.8.26":{"default":{"path":"StdStyle.sol/StdStyle.json","build_id":"dd64a528eb91b370e71884f52bdf5b7d"}}}},"seenByCompiler":true},"lib/forge-std/src/StdUtils.sol":{"lastModificationDate":1740402135688,"contentHash":"d5ff36b0cdb1b976dd77ae53fe96d0c6","sourceName":"lib/forge-std/src/StdUtils.sol","imports":["lib/forge-std/src/Vm.sol","lib/forge-std/src/interfaces/IMulticall3.sol"],"versionRequirement":">=0.6.2, <0.9.0","artifacts":{"StdUtils":{"0.8.26":{"default":{"path":"StdUtils.sol/StdUtils.json","build_id":"dd64a528eb91b370e71884f52bdf5b7d"}}}},"seenByCompiler":true},"lib/forge-std/src/Test.sol":{"lastModificationDate":1740402135688,"contentHash":"bc9d74a0c612e1c2b66cca2973bcc803","sourceName":"lib/forge-std/src/Test.sol","imports":["lib/forge-std/lib/ds-test/src/test.sol","lib/forge-std/src/Base.sol","lib/forge-std/src/StdAssertions.sol","lib/forge-std/src/StdChains.sol","lib/forge-std/src/StdCheats.sol","lib/forge-std/src/StdError.sol","lib/forge-std/src/StdInvariant.sol","lib/forge-std/src/StdJson.sol","lib/forge-std/src/StdMath.sol","lib/forge-std/src/StdStorage.sol","lib/forge-std/src/StdStyle.sol","lib/forge-std/src/StdUtils.sol","lib/forge-std/src/Vm.sol","lib/forge-std/src/console.sol","lib/forge-std/src/console2.sol","lib/forge-std/src/interfaces/IMulticall3.sol"],"versionRequirement":">=0.6.2, <0.9.0","artifacts":{"Test":{"0.8.26":{"default":{"path":"Test.sol/Test.json","build_id":"dd64a528eb91b370e71884f52bdf5b7d"}}}},"seenByCompiler":true},"lib/forge-std/src/Vm.sol":{"lastModificationDate":1740402135688,"contentHash":"68cca88e2df06231acff7abb1f6bdea6","sourceName":"lib/forge-std/src/Vm.sol","imports":[],"versionRequirement":">=0.6.2, <0.9.0","artifacts":{"Vm":{"0.8.26":{"default":{"path":"Vm.sol/Vm.json","build_id":"dd64a528eb91b370e71884f52bdf5b7d"}}},"VmSafe":{"0.8.26":{"default":{"path":"Vm.sol/VmSafe.json","build_id":"dd64a528eb91b370e71884f52bdf5b7d"}}}},"seenByCompiler":true},"lib/forge-std/src/console.sol":{"lastModificationDate":1740402135689,"contentHash":"100b8a33b917da1147740d7ab8b0ded3","sourceName":"lib/forge-std/src/console.sol","imports":[],"versionRequirement":">=0.4.22, <0.9.0","artifacts":{"console":{"0.8.26":{"default":{"path":"console.sol/console.json","build_id":"dd64a528eb91b370e71884f52bdf5b7d"}}}},"seenByCompiler":true},"lib/forge-std/src/console2.sol":{"lastModificationDate":1740402135689,"contentHash":"2096b4e5f252c5df9909cccbe3d2da2e","sourceName":"lib/forge-std/src/console2.sol","imports":[],"versionRequirement":">=0.4.22, <0.9.0","artifacts":{"console2":{"0.8.26":{"default":{"path":"console2.sol/console2.json","build_id":"dd64a528eb91b370e71884f52bdf5b7d"}}}},"seenByCompiler":true},"lib/forge-std/src/interfaces/IMulticall3.sol":{"lastModificationDate":1740402036596,"contentHash":"7b131ca1ca32ef6378b7b9ad5488b901","sourceName":"lib/forge-std/src/interfaces/IMulticall3.sol","imports":[],"versionRequirement":">=0.6.2, <0.9.0","artifacts":{"IMulticall3":{"0.8.26":{"default":{"path":"IMulticall3.sol/IMulticall3.json","build_id":"dd64a528eb91b370e71884f52bdf5b7d"}}}},"seenByCompiler":true},"lib/openzeppelin-contracts/contracts/access/manager/AuthorityUtils.sol":{"lastModificationDate":1740402144280,"contentHash":"e96b8b2cce8bd8dd292b03bf9310e64a","sourceName":"lib/openzeppelin-contracts/contracts/access/manager/AuthorityUtils.sol","imports":["lib/openzeppelin-contracts/contracts/access/manager/IAuthority.sol"],"versionRequirement":"^0.8.20","artifacts":{"AuthorityUtils":{"0.8.26":{"default":{"path":"AuthorityUtils.sol/AuthorityUtils.json","build_id":"dd64a528eb91b370e71884f52bdf5b7d"}}}},"seenByCompiler":true},"lib/openzeppelin-contracts/contracts/access/manager/IAccessManaged.sol":{"lastModificationDate":1740402144176,"contentHash":"c1b6a9715af4a5093443761a8ac58963","sourceName":"lib/openzeppelin-contracts/contracts/access/manager/IAccessManaged.sol","imports":[],"versionRequirement":"^0.8.20","artifacts":{"IAccessManaged":{"0.8.26":{"default":{"path":"IAccessManaged.sol/IAccessManaged.json","build_id":"dd64a528eb91b370e71884f52bdf5b7d"}}}},"seenByCompiler":true},"lib/openzeppelin-contracts/contracts/access/manager/IAccessManager.sol":{"lastModificationDate":1740402144177,"contentHash":"f5bfc2059c6a66631aa5cb29b6f906f5","sourceName":"lib/openzeppelin-contracts/contracts/access/manager/IAccessManager.sol","imports":["lib/openzeppelin-contracts/contracts/utils/Panic.sol","lib/openzeppelin-contracts/contracts/utils/math/Math.sol","lib/openzeppelin-contracts/contracts/utils/math/SafeCast.sol","lib/openzeppelin-contracts/contracts/utils/types/Time.sol"],"versionRequirement":"^0.8.20","artifacts":{"IAccessManager":{"0.8.26":{"default":{"path":"IAccessManager.sol/IAccessManager.json","build_id":"dd64a528eb91b370e71884f52bdf5b7d"}}}},"seenByCompiler":true},"lib/openzeppelin-contracts/contracts/access/manager/IAuthority.sol":{"lastModificationDate":1740402144177,"contentHash":"c32de6180bb4898b96ebbcc4cc3a322d","sourceName":"lib/openzeppelin-contracts/contracts/access/manager/IAuthority.sol","imports":[],"versionRequirement":"^0.8.20","artifacts":{"IAuthority":{"0.8.26":{"default":{"path":"IAuthority.sol/IAuthority.json","build_id":"dd64a528eb91b370e71884f52bdf5b7d"}}}},"seenByCompiler":true},"lib/openzeppelin-contracts/contracts/interfaces/IERC1967.sol":{"lastModificationDate":1740402144179,"contentHash":"4e17c826a54a8ee1a185449d4695d07d","sourceName":"lib/openzeppelin-contracts/contracts/interfaces/IERC1967.sol","imports":[],"versionRequirement":"^0.8.20","artifacts":{"IERC1967":{"0.8.26":{"default":{"path":"IERC1967.sol/IERC1967.json","build_id":"dd64a528eb91b370e71884f52bdf5b7d"}}}},"seenByCompiler":true},"lib/openzeppelin-contracts/contracts/interfaces/draft-IERC1822.sol":{"lastModificationDate":1740402144180,"contentHash":"64a2b7a96950f0641c477993f3029477","sourceName":"lib/openzeppelin-contracts/contracts/interfaces/draft-IERC1822.sol","imports":[],"versionRequirement":"^0.8.20","artifacts":{"IERC1822Proxiable":{"0.8.26":{"default":{"path":"draft-IERC1822.sol/IERC1822Proxiable.json","build_id":"dd64a528eb91b370e71884f52bdf5b7d"}}}},"seenByCompiler":true},"lib/openzeppelin-contracts/contracts/interfaces/draft-IERC6093.sol":{"lastModificationDate":1740402144180,"contentHash":"267d92fe4de67b1bdb3302c08f387dbf","sourceName":"lib/openzeppelin-contracts/contracts/interfaces/draft-IERC6093.sol","imports":[],"versionRequirement":"^0.8.20","artifacts":{"IERC1155Errors":{"0.8.26":{"default":{"path":"draft-IERC6093.sol/IERC1155Errors.json","build_id":"dd64a528eb91b370e71884f52bdf5b7d"}}},"IERC20Errors":{"0.8.26":{"default":{"path":"draft-IERC6093.sol/IERC20Errors.json","build_id":"dd64a528eb91b370e71884f52bdf5b7d"}}},"IERC721Errors":{"0.8.26":{"default":{"path":"draft-IERC6093.sol/IERC721Errors.json","build_id":"dd64a528eb91b370e71884f52bdf5b7d"}}}},"seenByCompiler":true},"lib/openzeppelin-contracts/contracts/proxy/ERC1967/ERC1967Proxy.sol":{"lastModificationDate":1740402144185,"contentHash":"07e13052976ae13746455b10ebf3cff9","sourceName":"lib/openzeppelin-contracts/contracts/proxy/ERC1967/ERC1967Proxy.sol","imports":["lib/openzeppelin-contracts/contracts/interfaces/IERC1967.sol","lib/openzeppelin-contracts/contracts/proxy/ERC1967/ERC1967Utils.sol","lib/openzeppelin-contracts/contracts/proxy/Proxy.sol","lib/openzeppelin-contracts/contracts/proxy/beacon/IBeacon.sol","lib/openzeppelin-contracts/contracts/utils/Address.sol","lib/openzeppelin-contracts/contracts/utils/Errors.sol","lib/openzeppelin-contracts/contracts/utils/StorageSlot.sol"],"versionRequirement":"^0.8.22","artifacts":{"ERC1967Proxy":{"0.8.26":{"default":{"path":"ERC1967Proxy.sol/ERC1967Proxy.json","build_id":"dd64a528eb91b370e71884f52bdf5b7d"}}}},"seenByCompiler":true},"lib/openzeppelin-contracts/contracts/proxy/ERC1967/ERC1967Utils.sol":{"lastModificationDate":1740402144185,"contentHash":"c023a5b23ee35b40b3085e550ff3367f","sourceName":"lib/openzeppelin-contracts/contracts/proxy/ERC1967/ERC1967Utils.sol","imports":["lib/openzeppelin-contracts/contracts/interfaces/IERC1967.sol","lib/openzeppelin-contracts/contracts/proxy/beacon/IBeacon.sol","lib/openzeppelin-contracts/contracts/utils/Address.sol","lib/openzeppelin-contracts/contracts/utils/Errors.sol","lib/openzeppelin-contracts/contracts/utils/StorageSlot.sol"],"versionRequirement":"^0.8.22","artifacts":{"ERC1967Utils":{"0.8.26":{"default":{"path":"ERC1967Utils.sol/ERC1967Utils.json","build_id":"dd64a528eb91b370e71884f52bdf5b7d"}}}},"seenByCompiler":true},"lib/openzeppelin-contracts/contracts/proxy/Proxy.sol":{"lastModificationDate":1740402144185,"contentHash":"35308c2fa7be99a959494c37e8257c16","sourceName":"lib/openzeppelin-contracts/contracts/proxy/Proxy.sol","imports":[],"versionRequirement":"^0.8.20","artifacts":{"Proxy":{"0.8.26":{"default":{"path":"Proxy.sol/Proxy.json","build_id":"dd64a528eb91b370e71884f52bdf5b7d"}}}},"seenByCompiler":true},"lib/openzeppelin-contracts/contracts/proxy/beacon/IBeacon.sol":{"lastModificationDate":1740402144185,"contentHash":"0a5c323fd908535580597848b8e550fb","sourceName":"lib/openzeppelin-contracts/contracts/proxy/beacon/IBeacon.sol","imports":[],"versionRequirement":"^0.8.20","artifacts":{"IBeacon":{"0.8.26":{"default":{"path":"IBeacon.sol/IBeacon.json","build_id":"dd64a528eb91b370e71884f52bdf5b7d"}}}},"seenByCompiler":true},"lib/openzeppelin-contracts/contracts/proxy/utils/Initializable.sol":{"lastModificationDate":1740402144185,"contentHash":"f0cedd674b4863ee90d1521a92ab82df","sourceName":"lib/openzeppelin-contracts/contracts/proxy/utils/Initializable.sol","imports":[],"versionRequirement":"^0.8.20","artifacts":{"Initializable":{"0.8.26":{"default":{"path":"Initializable.sol/Initializable.json","build_id":"dd64a528eb91b370e71884f52bdf5b7d"}}}},"seenByCompiler":true},"lib/openzeppelin-contracts/contracts/token/ERC20/IERC20.sol":{"lastModificationDate":1740402144186,"contentHash":"8f19f64d2adadf448840908bbaf431c8","sourceName":"lib/openzeppelin-contracts/contracts/token/ERC20/IERC20.sol","imports":[],"versionRequirement":"^0.8.20","artifacts":{"IERC20":{"0.8.26":{"default":{"path":"IERC20.sol/IERC20.json","build_id":"dd64a528eb91b370e71884f52bdf5b7d"}}}},"seenByCompiler":true},"lib/openzeppelin-contracts/contracts/token/ERC20/extensions/IERC20Metadata.sol":{"lastModificationDate":1740402144187,"contentHash":"794db3115001aa372c79326fcfd44b1f","sourceName":"lib/openzeppelin-contracts/contracts/token/ERC20/extensions/IERC20Metadata.sol","imports":["lib/openzeppelin-contracts/contracts/token/ERC20/IERC20.sol"],"versionRequirement":"^0.8.20","artifacts":{"IERC20Metadata":{"0.8.26":{"default":{"path":"IERC20Metadata.sol/IERC20Metadata.json","build_id":"dd64a528eb91b370e71884f52bdf5b7d"}}}},"seenByCompiler":true},"lib/openzeppelin-contracts/contracts/utils/Address.sol":{"lastModificationDate":1740402144188,"contentHash":"5b9a49c25d7edbc48ffcbd2c7e8a40ef","sourceName":"lib/openzeppelin-contracts/contracts/utils/Address.sol","imports":["lib/openzeppelin-contracts/contracts/utils/Errors.sol"],"versionRequirement":"^0.8.20","artifacts":{"Address":{"0.8.26":{"default":{"path":"Address.sol/Address.json","build_id":"dd64a528eb91b370e71884f52bdf5b7d"}}}},"seenByCompiler":true},"lib/openzeppelin-contracts/contracts/utils/Errors.sol":{"lastModificationDate":1740402144189,"contentHash":"6b5eac2b85500c3012977849cfd633d8","sourceName":"lib/openzeppelin-contracts/contracts/utils/Errors.sol","imports":[],"versionRequirement":"^0.8.20","artifacts":{"Errors":{"0.8.26":{"default":{"path":"Errors.sol/Errors.json","build_id":"dd64a528eb91b370e71884f52bdf5b7d"}}}},"seenByCompiler":true},"lib/openzeppelin-contracts/contracts/utils/Panic.sol":{"lastModificationDate":1740402144189,"contentHash":"2133dc13536b4a6a98131e431fac59e1","sourceName":"lib/openzeppelin-contracts/contracts/utils/Panic.sol","imports":[],"versionRequirement":"^0.8.20","artifacts":{"Panic":{"0.8.26":{"default":{"path":"Panic.sol/Panic.json","build_id":"dd64a528eb91b370e71884f52bdf5b7d"}}}},"seenByCompiler":true},"lib/openzeppelin-contracts/contracts/utils/StorageSlot.sol":{"lastModificationDate":1740402144189,"contentHash":"e656d64c4ce918f3d13030b91c935134","sourceName":"lib/openzeppelin-contracts/contracts/utils/StorageSlot.sol","imports":[],"versionRequirement":"^0.8.20","artifacts":{"StorageSlot":{"0.8.26":{"default":{"path":"StorageSlot.sol/StorageSlot.json","build_id":"dd64a528eb91b370e71884f52bdf5b7d"}}}},"seenByCompiler":true},"lib/openzeppelin-contracts/contracts/utils/math/Math.sol":{"lastModificationDate":1740402144283,"contentHash":"2b2665ae9bdb1af440658741a77fe213","sourceName":"lib/openzeppelin-contracts/contracts/utils/math/Math.sol","imports":["lib/openzeppelin-contracts/contracts/utils/Panic.sol","lib/openzeppelin-contracts/contracts/utils/math/SafeCast.sol"],"versionRequirement":"^0.8.20","artifacts":{"Math":{"0.8.26":{"default":{"path":"Math.sol/Math.json","build_id":"dd64a528eb91b370e71884f52bdf5b7d"}}}},"seenByCompiler":true},"lib/openzeppelin-contracts/contracts/utils/math/SafeCast.sol":{"lastModificationDate":1740402144191,"contentHash":"2adca1150f58fc6f3d1f0a0f22ee7cca","sourceName":"lib/openzeppelin-contracts/contracts/utils/math/SafeCast.sol","imports":[],"versionRequirement":"^0.8.20","artifacts":{"SafeCast":{"0.8.26":{"default":{"path":"SafeCast.sol/SafeCast.json","build_id":"dd64a528eb91b370e71884f52bdf5b7d"}}}},"seenByCompiler":true},"lib/openzeppelin-contracts/contracts/utils/types/Time.sol":{"lastModificationDate":1740402144191,"contentHash":"d83e7814a059fc1287fd765f424ce004","sourceName":"lib/openzeppelin-contracts/contracts/utils/types/Time.sol","imports":["lib/openzeppelin-contracts/contracts/utils/Panic.sol","lib/openzeppelin-contracts/contracts/utils/math/Math.sol","lib/openzeppelin-contracts/contracts/utils/math/SafeCast.sol"],"versionRequirement":"^0.8.20","artifacts":{"Time":{"0.8.26":{"default":{"path":"Time.sol/Time.json","build_id":"dd64a528eb91b370e71884f52bdf5b7d"}}}},"seenByCompiler":true},"lib/openzeppelin-contracts-upgradeable/contracts/access/OwnableUpgradeable.sol":{"lastModificationDate":1740402152500,"contentHash":"77d30f3cd93f46b80b6f8f1ebc574ee4","sourceName":"lib/openzeppelin-contracts-upgradeable/contracts/access/OwnableUpgradeable.sol","imports":["lib/openzeppelin-contracts-upgradeable/contracts/proxy/utils/Initializable.sol","lib/openzeppelin-contracts-upgradeable/contracts/utils/ContextUpgradeable.sol"],"versionRequirement":"^0.8.20","artifacts":{"OwnableUpgradeable":{"0.8.26":{"default":{"path":"OwnableUpgradeable.sol/OwnableUpgradeable.json","build_id":"dd64a528eb91b370e71884f52bdf5b7d"}}}},"seenByCompiler":true},"lib/openzeppelin-contracts-upgradeable/contracts/access/manager/AccessManagedUpgradeable.sol":{"lastModificationDate":1740402152500,"contentHash":"3227ed5ac4d0d829c26200d13b8e2e69","sourceName":"lib/openzeppelin-contracts-upgradeable/contracts/access/manager/AccessManagedUpgradeable.sol","imports":["lib/openzeppelin-contracts/contracts/access/manager/AuthorityUtils.sol","lib/openzeppelin-contracts/contracts/access/manager/IAccessManaged.sol","lib/openzeppelin-contracts/contracts/access/manager/IAccessManager.sol","lib/openzeppelin-contracts/contracts/access/manager/IAuthority.sol","lib/openzeppelin-contracts/contracts/utils/Panic.sol","lib/openzeppelin-contracts/contracts/utils/math/Math.sol","lib/openzeppelin-contracts/contracts/utils/math/SafeCast.sol","lib/openzeppelin-contracts/contracts/utils/types/Time.sol","lib/openzeppelin-contracts-upgradeable/contracts/proxy/utils/Initializable.sol","lib/openzeppelin-contracts-upgradeable/contracts/utils/ContextUpgradeable.sol"],"versionRequirement":"^0.8.20","artifacts":{"AccessManagedUpgradeable":{"0.8.26":{"default":{"path":"AccessManagedUpgradeable.sol/AccessManagedUpgradeable.json","build_id":"dd64a528eb91b370e71884f52bdf5b7d"}}}},"seenByCompiler":true},"lib/openzeppelin-contracts-upgradeable/contracts/proxy/utils/Initializable.sol":{"lastModificationDate":1740402152509,"contentHash":"f0cedd674b4863ee90d1521a92ab82df","sourceName":"lib/openzeppelin-contracts-upgradeable/contracts/proxy/utils/Initializable.sol","imports":[],"versionRequirement":"^0.8.20","artifacts":{"Initializable":{"0.8.26":{"default":{"path":"utils/Initializable.sol/Initializable.json","build_id":"dd64a528eb91b370e71884f52bdf5b7d"}}}},"seenByCompiler":true},"lib/openzeppelin-contracts-upgradeable/contracts/proxy/utils/UUPSUpgradeable.sol":{"lastModificationDate":1740402152597,"contentHash":"ac3b77dea52cfdb14498e0a306a34b01","sourceName":"lib/openzeppelin-contracts-upgradeable/contracts/proxy/utils/UUPSUpgradeable.sol","imports":["lib/openzeppelin-contracts/contracts/interfaces/IERC1967.sol","lib/openzeppelin-contracts/contracts/interfaces/draft-IERC1822.sol","lib/openzeppelin-contracts/contracts/proxy/ERC1967/ERC1967Utils.sol","lib/openzeppelin-contracts/contracts/proxy/beacon/IBeacon.sol","lib/openzeppelin-contracts/contracts/utils/Address.sol","lib/openzeppelin-contracts/contracts/utils/Errors.sol","lib/openzeppelin-contracts/contracts/utils/StorageSlot.sol","lib/openzeppelin-contracts-upgradeable/contracts/proxy/utils/Initializable.sol"],"versionRequirement":"^0.8.22","artifacts":{"UUPSUpgradeable":{"0.8.26":{"default":{"path":"UUPSUpgradeable.sol/UUPSUpgradeable.json","build_id":"dd64a528eb91b370e71884f52bdf5b7d"}}}},"seenByCompiler":true},"lib/openzeppelin-contracts-upgradeable/contracts/token/ERC20/ERC20Upgradeable.sol":{"lastModificationDate":1740402152510,"contentHash":"c5dd6da834c5a0a8d9bb8353da2994b7","sourceName":"lib/openzeppelin-contracts-upgradeable/contracts/token/ERC20/ERC20Upgradeable.sol","imports":["lib/openzeppelin-contracts/contracts/interfaces/draft-IERC6093.sol","lib/openzeppelin-contracts/contracts/token/ERC20/IERC20.sol","lib/openzeppelin-contracts/contracts/token/ERC20/extensions/IERC20Metadata.sol","lib/openzeppelin-contracts-upgradeable/contracts/proxy/utils/Initializable.sol","lib/openzeppelin-contracts-upgradeable/contracts/utils/ContextUpgradeable.sol"],"versionRequirement":"^0.8.20","artifacts":{"ERC20Upgradeable":{"0.8.26":{"default":{"path":"ERC20Upgradeable.sol/ERC20Upgradeable.json","build_id":"dd64a528eb91b370e71884f52bdf5b7d"}}}},"seenByCompiler":true},"lib/openzeppelin-contracts-upgradeable/contracts/token/ERC20/extensions/ERC20PausableUpgradeable.sol":{"lastModificationDate":1740402152597,"contentHash":"34ef569443b2619982c62a3eb590ae5d","sourceName":"lib/openzeppelin-contracts-upgradeable/contracts/token/ERC20/extensions/ERC20PausableUpgradeable.sol","imports":["lib/openzeppelin-contracts/contracts/interfaces/draft-IERC6093.sol","lib/openzeppelin-contracts/contracts/token/ERC20/IERC20.sol","lib/openzeppelin-contracts/contracts/token/ERC20/extensions/IERC20Metadata.sol","lib/openzeppelin-contracts-upgradeable/contracts/proxy/utils/Initializable.sol","lib/openzeppelin-contracts-upgradeable/contracts/token/ERC20/ERC20Upgradeable.sol","lib/openzeppelin-contracts-upgradeable/contracts/utils/ContextUpgradeable.sol","lib/openzeppelin-contracts-upgradeable/contracts/utils/PausableUpgradeable.sol"],"versionRequirement":"^0.8.20","artifacts":{"ERC20PausableUpgradeable":{"0.8.26":{"default":{"path":"ERC20PausableUpgradeable.sol/ERC20PausableUpgradeable.json","build_id":"dd64a528eb91b370e71884f52bdf5b7d"}}}},"seenByCompiler":true},"lib/openzeppelin-contracts-upgradeable/contracts/utils/ContextUpgradeable.sol":{"lastModificationDate":1740402152512,"contentHash":"c28aaa25d083a9a55bd9ec9e0b785122","sourceName":"lib/openzeppelin-contracts-upgradeable/contracts/utils/ContextUpgradeable.sol","imports":["lib/openzeppelin-contracts-upgradeable/contracts/proxy/utils/Initializable.sol"],"versionRequirement":"^0.8.20","artifacts":{"ContextUpgradeable":{"0.8.26":{"default":{"path":"ContextUpgradeable.sol/ContextUpgradeable.json","build_id":"dd64a528eb91b370e71884f52bdf5b7d"}}}},"seenByCompiler":true},"lib/openzeppelin-contracts-upgradeable/contracts/utils/PausableUpgradeable.sol":{"lastModificationDate":1740402152598,"contentHash":"ef20fd32f5bdcc50bd466abc8fc7f181","sourceName":"lib/openzeppelin-contracts-upgradeable/contracts/utils/PausableUpgradeable.sol","imports":["lib/openzeppelin-contracts-upgradeable/contracts/proxy/utils/Initializable.sol","lib/openzeppelin-contracts-upgradeable/contracts/utils/ContextUpgradeable.sol"],"versionRequirement":"^0.8.20","artifacts":{"PausableUpgradeable":{"0.8.26":{"default":{"path":"PausableUpgradeable.sol/PausableUpgradeable.json","build_id":"dd64a528eb91b370e71884f52bdf5b7d"}}}},"seenByCompiler":true},"script/DeployEngine.s.sol":{"lastModificationDate":1740657683174,"contentHash":"f02a2b8f621f717338d39ccbf0a041f6","sourceName":"script/DeployEngine.s.sol","imports":["lib/forge-std/src/Base.sol","lib/forge-std/src/Script.sol","lib/forge-std/src/StdChains.sol","lib/forge-std/src/StdCheats.sol","lib/forge-std/src/StdJson.sol","lib/forge-std/src/StdMath.sol","lib/forge-std/src/StdStorage.sol","lib/forge-std/src/StdUtils.sol","lib/forge-std/src/Vm.sol","lib/forge-std/src/console.sol","lib/forge-std/src/console2.sol","lib/forge-std/src/interfaces/IMulticall3.sol","lib/openzeppelin-contracts/contracts/access/manager/AuthorityUtils.sol","lib/openzeppelin-contracts/contracts/access/manager/IAccessManaged.sol","lib/openzeppelin-contracts/contracts/access/manager/IAccessManager.sol","lib/openzeppelin-contracts/contracts/access/manager/IAuthority.sol","lib/openzeppelin-contracts/contracts/interfaces/IERC1967.sol","lib/openzeppelin-contracts/contracts/interfaces/draft-IERC1822.sol","lib/openzeppelin-contracts/contracts/interfaces/draft-IERC6093.sol","lib/openzeppelin-contracts/contracts/proxy/ERC1967/ERC1967Proxy.sol","lib/openzeppelin-contracts/contracts/proxy/ERC1967/ERC1967Utils.sol","lib/openzeppelin-contracts/contracts/proxy/Proxy.sol","lib/openzeppelin-contracts/contracts/proxy/beacon/IBeacon.sol","lib/openzeppelin-contracts/contracts/proxy/utils/Initializable.sol","lib/openzeppelin-contracts/contracts/token/ERC20/IERC20.sol","lib/openzeppelin-contracts/contracts/token/ERC20/extensions/IERC20Metadata.sol","lib/openzeppelin-contracts/contracts/utils/Address.sol","lib/openzeppelin-contracts/contracts/utils/Errors.sol","lib/openzeppelin-contracts/contracts/utils/Panic.sol","lib/openzeppelin-contracts/contracts/utils/StorageSlot.sol","lib/openzeppelin-contracts/contracts/utils/math/Math.sol","lib/openzeppelin-contracts/contracts/utils/math/SafeCast.sol","lib/openzeppelin-contracts/contracts/utils/types/Time.sol","lib/openzeppelin-contracts-upgradeable/contracts/access/OwnableUpgradeable.sol","lib/openzeppelin-contracts-upgradeable/contracts/access/manager/AccessManagedUpgradeable.sol","lib/openzeppelin-contracts-upgradeable/contracts/proxy/utils/Initializable.sol","lib/openzeppelin-contracts-upgradeable/contracts/proxy/utils/UUPSUpgradeable.sol","lib/openzeppelin-contracts-upgradeable/contracts/token/ERC20/ERC20Upgradeable.sol","lib/openzeppelin-contracts-upgradeable/contracts/token/ERC20/extensions/ERC20PausableUpgradeable.sol","lib/openzeppelin-contracts-upgradeable/contracts/utils/ContextUpgradeable.sol","lib/openzeppelin-contracts-upgradeable/contracts/utils/PausableUpgradeable.sol","src/BTtokens.sol","src/BTtokensEngine.sol","src/Blacklistable.sol"],"versionRequirement":"^0.8.24","artifacts":{"DeployEngine":{"0.8.26":{"default":{"path":"DeployEngine.s.sol/DeployEngine.json","build_id":"b551acfee626ac9c7ca19e40e93d7b0b"}}}},"seenByCompiler":true},"src/BTtokens.sol":{"lastModificationDate":1740595774955,"contentHash":"7157c97291271f403b8942562d5791f7","sourceName":"src/BTtokens.sol","imports":["lib/openzeppelin-contracts/contracts/access/manager/AuthorityUtils.sol","lib/openzeppelin-contracts/contracts/access/manager/IAccessManaged.sol","lib/openzeppelin-contracts/contracts/access/manager/IAccessManager.sol","lib/openzeppelin-contracts/contracts/access/manager/IAuthority.sol","lib/openzeppelin-contracts/contracts/interfaces/IERC1967.sol","lib/openzeppelin-contracts/contracts/interfaces/draft-IERC1822.sol","lib/openzeppelin-contracts/contracts/interfaces/draft-IERC6093.sol","lib/openzeppelin-contracts/contracts/proxy/ERC1967/ERC1967Proxy.sol","lib/openzeppelin-contracts/contracts/proxy/ERC1967/ERC1967Utils.sol","lib/openzeppelin-contracts/contracts/proxy/Proxy.sol","lib/openzeppelin-contracts/contracts/proxy/beacon/IBeacon.sol","lib/openzeppelin-contracts/contracts/proxy/utils/Initializable.sol","lib/openzeppelin-contracts/contracts/token/ERC20/IERC20.sol","lib/openzeppelin-contracts/contracts/token/ERC20/extensions/IERC20Metadata.sol","lib/openzeppelin-contracts/contracts/utils/Address.sol","lib/openzeppelin-contracts/contracts/utils/Errors.sol","lib/openzeppelin-contracts/contracts/utils/Panic.sol","lib/openzeppelin-contracts/contracts/utils/StorageSlot.sol","lib/openzeppelin-contracts/contracts/utils/math/Math.sol","lib/openzeppelin-contracts/contracts/utils/math/SafeCast.sol","lib/openzeppelin-contracts/contracts/utils/types/Time.sol","lib/openzeppelin-contracts-upgradeable/contracts/access/OwnableUpgradeable.sol","lib/openzeppelin-contracts-upgradeable/contracts/access/manager/AccessManagedUpgradeable.sol","lib/openzeppelin-contracts-upgradeable/contracts/proxy/utils/Initializable.sol","lib/openzeppelin-contracts-upgradeable/contracts/proxy/utils/UUPSUpgradeable.sol","lib/openzeppelin-contracts-upgradeable/contracts/token/ERC20/ERC20Upgradeable.sol","lib/openzeppelin-contracts-upgradeable/contracts/token/ERC20/extensions/ERC20PausableUpgradeable.sol","lib/openzeppelin-contracts-upgradeable/contracts/utils/ContextUpgradeable.sol","lib/openzeppelin-contracts-upgradeable/contracts/utils/PausableUpgradeable.sol","src/BTtokensEngine.sol","src/Blacklistable.sol"],"versionRequirement":"^0.8.24","artifacts":{"BTtokens":{"0.8.26":{"default":{"path":"BTtokens.sol/BTtokens.json","build_id":"b551acfee626ac9c7ca19e40e93d7b0b"}}}},"seenByCompiler":true},"src/BTtokensEngine.sol":{"lastModificationDate":1740657257344,"contentHash":"25a226e9b52544168fbb205b8badb7b8","sourceName":"src/BTtokensEngine.sol","imports":["lib/openzeppelin-contracts/contracts/interfaces/IERC1967.sol","lib/openzeppelin-contracts/contracts/interfaces/draft-IERC1822.sol","lib/openzeppelin-contracts/contracts/proxy/ERC1967/ERC1967Proxy.sol","lib/openzeppelin-contracts/contracts/proxy/ERC1967/ERC1967Utils.sol","lib/openzeppelin-contracts/contracts/proxy/Proxy.sol","lib/openzeppelin-contracts/contracts/proxy/beacon/IBeacon.sol","lib/openzeppelin-contracts/contracts/utils/Address.sol","lib/openzeppelin-contracts/contracts/utils/Errors.sol","lib/openzeppelin-contracts/contracts/utils/StorageSlot.sol","lib/openzeppelin-contracts-upgradeable/contracts/access/OwnableUpgradeable.sol","lib/openzeppelin-contracts-upgradeable/contracts/proxy/utils/Initializable.sol","lib/openzeppelin-contracts-upgradeable/contracts/proxy/utils/UUPSUpgradeable.sol","lib/openzeppelin-contracts-upgradeable/contracts/utils/ContextUpgradeable.sol"],"versionRequirement":"^0.8.24","artifacts":{"BTtokenProxy":{"0.8.26":{"default":{"path":"BTtokensEngine.sol/BTtokenProxy.json","build_id":"b551acfee626ac9c7ca19e40e93d7b0b"}}},"BTtokensEngine":{"0.8.26":{"default":{"path":"BTtokensEngine.sol/BTtokensEngine.json","build_id":"b551acfee626ac9c7ca19e40e93d7b0b"}}}},"seenByCompiler":true},"src/Blacklistable.sol":{"lastModificationDate":1740402572331,"contentHash":"cc203da76e2adf9a6bd605872186d191","sourceName":"src/Blacklistable.sol","imports":["lib/openzeppelin-contracts-upgradeable/contracts/access/OwnableUpgradeable.sol","lib/openzeppelin-contracts-upgradeable/contracts/proxy/utils/Initializable.sol","lib/openzeppelin-contracts-upgradeable/contracts/utils/ContextUpgradeable.sol"],"versionRequirement":"^0.8.24","artifacts":{"Blacklistable":{"0.8.26":{"default":{"path":"Blacklistable.sol/Blacklistable.json","build_id":"dd64a528eb91b370e71884f52bdf5b7d"}}}},"seenByCompiler":true},"test/DeployAndUpgradeTokenImplementation.t.sol":{"lastModificationDate":1740657738607,"contentHash":"6cccb19100c99a8ba25bb1e924872025","sourceName":"test/DeployAndUpgradeTokenImplementation.t.sol","imports":["lib/forge-std/lib/ds-test/src/test.sol","lib/forge-std/src/Base.sol","lib/forge-std/src/Script.sol","lib/forge-std/src/StdAssertions.sol","lib/forge-std/src/StdChains.sol","lib/forge-std/src/StdCheats.sol","lib/forge-std/src/StdError.sol","lib/forge-std/src/StdInvariant.sol","lib/forge-std/src/StdJson.sol","lib/forge-std/src/StdMath.sol","lib/forge-std/src/StdStorage.sol","lib/forge-std/src/StdStyle.sol","lib/forge-std/src/StdUtils.sol","lib/forge-std/src/Test.sol","lib/forge-std/src/Vm.sol","lib/forge-std/src/console.sol","lib/forge-std/src/console2.sol","lib/forge-std/src/interfaces/IMulticall3.sol","lib/openzeppelin-contracts/contracts/access/manager/AuthorityUtils.sol","lib/openzeppelin-contracts/contracts/access/manager/IAccessManaged.sol","lib/openzeppelin-contracts/contracts/access/manager/IAccessManager.sol","lib/openzeppelin-contracts/contracts/access/manager/IAuthority.sol","lib/openzeppelin-contracts/contracts/interfaces/IERC1967.sol","lib/openzeppelin-contracts/contracts/interfaces/draft-IERC1822.sol","lib/openzeppelin-contracts/contracts/interfaces/draft-IERC6093.sol","lib/openzeppelin-contracts/contracts/proxy/ERC1967/ERC1967Proxy.sol","lib/openzeppelin-contracts/contracts/proxy/ERC1967/ERC1967Utils.sol","lib/openzeppelin-contracts/contracts/proxy/Proxy.sol","lib/openzeppelin-contracts/contracts/proxy/beacon/IBeacon.sol","lib/openzeppelin-contracts/contracts/proxy/utils/Initializable.sol","lib/openzeppelin-contracts/contracts/token/ERC20/IERC20.sol","lib/openzeppelin-contracts/contracts/token/ERC20/extensions/IERC20Metadata.sol","lib/openzeppelin-contracts/contracts/utils/Address.sol","lib/openzeppelin-contracts/contracts/utils/Errors.sol","lib/openzeppelin-contracts/contracts/utils/Panic.sol","lib/openzeppelin-contracts/contracts/utils/StorageSlot.sol","lib/openzeppelin-contracts/contracts/utils/math/Math.sol","lib/openzeppelin-contracts/contracts/utils/math/SafeCast.sol","lib/openzeppelin-contracts/contracts/utils/types/Time.sol","lib/openzeppelin-contracts-upgradeable/contracts/access/OwnableUpgradeable.sol","lib/openzeppelin-contracts-upgradeable/contracts/access/manager/AccessManagedUpgradeable.sol","lib/openzeppelin-contracts-upgradeable/contracts/proxy/utils/Initializable.sol","lib/openzeppelin-contracts-upgradeable/contracts/proxy/utils/UUPSUpgradeable.sol","lib/openzeppelin-contracts-upgradeable/contracts/token/ERC20/ERC20Upgradeable.sol","lib/openzeppelin-contracts-upgradeable/contracts/token/ERC20/extensions/ERC20PausableUpgradeable.sol","lib/openzeppelin-contracts-upgradeable/contracts/utils/ContextUpgradeable.sol","lib/openzeppelin-contracts-upgradeable/contracts/utils/PausableUpgradeable.sol","script/DeployEngine.s.sol","src/BTtokens.sol","src/BTtokensEngine.sol","src/Blacklistable.sol"],"versionRequirement":"^0.8.18","artifacts":{"DeployAndUpgradeTest":{"0.8.26":{"default":{"path":"DeployAndUpgradeTokenImplementation.t.sol/DeployAndUpgradeTest.json","build_id":"b551acfee626ac9c7ca19e40e93d7b0b"}}}},"seenByCompiler":true}},"builds":["b551acfee626ac9c7ca19e40e93d7b0b","dd64a528eb91b370e71884f52bdf5b7d"],"profiles":{"default":{"solc":{"optimizer":{"enabled":true,"runs":200},"metadata":{"useLiteralContent":false,"bytecodeHash":"ipfs","appendCBOR":true},"outputSelection":{"*":{"*":["abi","evm.bytecode.object","evm.bytecode.sourceMap","evm.bytecode.linkReferences","evm.deployedBytecode.object","evm.deployedBytecode.sourceMap","evm.deployedBytecode.linkReferences","evm.deployedBytecode.immutableReferences","evm.methodIdentifiers","metadata"]}},"evmVersion":"cancun","viaIR":false,"libraries":{}},"vyper":{"evmVersion":"cancun","outputSelection":{"*":{"*":["abi","evm.bytecode","evm.deployedBytecode"]}}}}}}